{
	"info": {
		"_postman_id": "ddb75e8c-f147-4a9e-8739-c142724ba0c9",
		"name": "Product-Service",
		"schema": "https://schema.getpostman.com/json/collection/v2.1.0/collection.json",
		"_exporter_id": "13877790"
	},
	"item": [
		{
			"name": "GetAll",
			"request": {
				"method": "GET",
				"header": [],
				"url": {
					"raw": "localhost:8081/api/v1/products",
					"host": [
						"localhost"
					],
					"port": "8081",
					"path": [
						"api",
						"v1",
						"products"
					]
				}
			},
			"response": []
		},
		{
			"name": "Post Product",
			"request": {
				"method": "POST",
				"header": [],
				"body": {
					"mode": "raw",
					"raw": "{\n    \"productName\": \"Apple\",\n    \"quantity\": 44\n}\n\n",
					"options": {
						"raw": {
							"language": "json"
						}
					}
				},
				"url": {
					"raw": "http://localhost:8081/api/v1/products",
					"protocol": "http",
					"host": [
						"localhost"
					],
					"port": "8081",
					"path": [
						"api",
						"v1",
						"products"
					]
				}
			},
			"response": []
		},
		{
			"name": "Post Product null code",
			"request": {
				"method": "POST",
				"header": [],
				"body": {
					"mode": "raw",
					"raw": "{\n    \"productName\": \"Apple\",\n    \"quantity\": 44\n}\n\n",
					"options": {
						"raw": {
							"language": "json"
						}
					}
				},
				"url": {
					"raw": "http://localhost:8081/api/v1/products",
					"protocol": "http",
					"host": [
						"localhost"
					],
					"port": "8081",
					"path": [
						"api",
						"v1",
						"products"
					]
				}
			},
			"response": []
		},
		{
			"name": "Post Product Samsung",
			"request": {
				"method": "POST",
				"header": [],
				"body": {
					"mode": "raw",
					"raw": "{\n    \"productName\": \"SamsungS22\",\n    \"quantity\": 0,\n    \"price\":22.06\n}\n",
					"options": {
						"raw": {
							"language": "json"
						}
					}
				},
				"url": {
					"raw": "http://localhost:8081/api/v1/products",
					"protocol": "http",
					"host": [
						"localhost"
					],
					"port": "8081",
					"path": [
						"api",
						"v1",
						"products"
					]
				}
			},
			"response": []
		},
		{
			"name": "Null checker",
			"request": {
				"method": "POST",
				"header": [],
				"body": {
					"mode": "raw",
					"raw": "{\n    \"productName\": \"Samsung S22\",\n    \"quantity\": 55\n}\n",
					"options": {
						"raw": {
							"language": "json"
						}
					}
				},
				"url": {
					"raw": "http://localhost:8081/api/v1/products",
					"protocol": "http",
					"host": [
						"localhost"
					],
					"port": "8081",
					"path": [
						"api",
						"v1",
						"products"
					]
				}
			},
			"response": []
		},
		{
			"name": "Get One Product By UUID",
			"request": {
				"method": "GET",
				"header": [],
				"url": {
					"raw": "localhost:8081/api/v1/product/uuid/52dc8800-5a40-4f1e-8478-7d86c7a0eed9",
					"host": [
						"localhost"
					],
					"port": "8081",
					"path": [
						"api",
						"v1",
						"product",
						"uuid",
						"52dc8800-5a40-4f1e-8478-7d86c7a0eed9"
					]
				}
			},
			"response": []
		},
		{
			"name": "Get One or More Product By Name",
			"request": {
				"method": "GET",
				"header": [],
				"url": {
					"raw": "localhost:8081/api/v1/product/SamsungS22",
					"host": [
						"localhost"
					],
					"port": "8081",
					"path": [
						"api",
						"v1",
						"product",
						"SamsungS22"
					]
				}
			},
			"response": []
		},
		{
			"name": "Get One or More Product By Name Copy",
			"request": {
				"method": "GET",
				"header": [],
				"url": {
					"raw": "localhost:8081/api/v1/product/code/AA164",
					"host": [
						"localhost"
					],
					"port": "8081",
					"path": [
						"api",
						"v1",
						"product",
						"code",
						"AA164"
					]
				}
			},
			"response": []
		}
	]
}